pyrocketbot/__init__.py
pyrocketbot/client.py
pyrocketbot-1.0.5.dist-info/METADATA
pyrocketbot-1.0.5.dist-info/WHEEL
pyrocketbot-1.0.5.dist-info/top_level.txt
pyrocketbot-1.0.5.dist-info/RECORD
