Metadata-Version: 2.1
Name: pyrocketbot
Version: 1.0.5
Summary: Python lib for create rocketchat bot with getupdate like TelegramBots
Author-email: "SeYeD Mohammad Khoshnava | seyed.dev" <me@seyed.dev>
Project-URL: Homepage, https://github.com/seyed-dev/rocketchatbot
Keywords: rocketchat,bot,rocket.chat
Classifier: License :: OSI Approved :: MIT License
Classifier: Programming Language :: Python
Classifier: Programming Language :: Python :: 3
Requires-Python: >=3.9
Requires-Dist: rocketchat-API
